aws_batch.py
setup.py
aws_batch.egg-info/PKG-INFO
aws_batch.egg-info/SOURCES.txt
aws_batch.egg-info/dependency_links.txt
aws_batch.egg-info/entry_points.txt
aws_batch.egg-info/requires.txt
aws_batch.egg-info/top_level.txt