Metadata-Version: 1.2
Name: aws-batch
Version: 0.6
Summary: AWS Batch helper
Home-page: https://github.com/crosenth/aws_batch
Author: Chris Rosenthal
Author-email: crosenth@gmail.com
License: GPLv3
Keywords: aws,batch,s3,awscli,boto3
Platform: UNKNOWN
Classifier: License :: OSI Approved :: GNU General Public License v3 (GPLv3)
Classifier: Development Status :: 4 - Beta
Classifier: Environment :: Console
Classifier: Operating System :: OS Independent
Classifier: Intended Audience :: End Users/Desktop
Classifier: License :: OSI Approved :: GNU General Public License v3 (GPLv3)
Classifier: Programming Language :: Python :: 3 :: Only
Requires-Python: >=3.3
